motipy/__init__.py
motipy/motipy.py
motipy-2.0.0.dist-info/LICENSE
motipy-2.0.0.dist-info/METADATA
motipy-2.0.0.dist-info/WHEEL
motipy-2.0.0.dist-info/top_level.txt
motipy-2.0.0.dist-info/RECORD
