Metadata-Version: 2.1
Name: motipy
Version: 2.0.0
Summary: Un package Python pour obtenir des messages de motivation.
Author: Coding Team
Author-email: codingteam@telegmail.com
License: MIT
Classifier: Programming Language :: Python :: 3
Classifier: Topic :: Utilities
Requires-Python: >=3.7
License-File: LICENSE
